{
  "editor": {
    "default": "nvim",
    "args": "",
    "system-specific": {}
  },
  "explorer": {
    "default": "ranger",
    "args": "",
    "system-specific": {}
  },
  "ide": {
    "default": "zed",
    "args": "",
    "system-specific": {}
  },
  "ai-cli": {
    "default": "aichat",
    "args": "",
    "system-specific": {}
  },
  "projects": "~/Developer",
  "required": {
    "default": ["fzf", "gh", "git", "sponge", "jq"],
    "system-specific": {}
  },
  "configs": [
    {
      "cmd": "nvim",
      "paths": ["~/.config/nim"],
      "checks": {}
    },
    {
      "cmd": "aichat",
      "paths": ["~/.config/aichat"],
      "system-specific": {
        "Darwin": ["~/.config/aichat"]
      }
    }
  ]
}
